olang_resolver_test/__init__.py
olang_resolver_test/__main__.py
olang_resolver_test/badge.py
olang_resolver_test/cli.py
olang_resolver_test/conformance.py
olang_resolver_test/resolver_loader.py
olang_resolver_test/test_suite.py
olang_resolver_test-0.1.5.dist-info/licenses/LICENSE
olang_resolver_test-0.1.5.dist-info/METADATA
olang_resolver_test-0.1.5.dist-info/WHEEL
olang_resolver_test-0.1.5.dist-info/entry_points.txt
olang_resolver_test-0.1.5.dist-info/top_level.txt
olang_resolver_test-0.1.5.dist-info/RECORD
