Metadata-Version: 2.4
Name: olang-resolver-test
Version: 0.1.5
Summary: O-lang resolver conformance and certification toolkit
Author-email: Olalekan Ogundipe <4olamy1@gmail.com>
Maintainer-email: O-Lang Foundation <4olamy1@gmail.com>
License-Expression: MIT
Project-URL: Homepage, https://github.com/O-Lang-Central/python-olang-tester
Project-URL: Repository, https://github.com/O-Lang-Central/python-olang-tester
Classifier: Development Status :: 4 - Beta
Classifier: Intended Audience :: Developers
Classifier: Programming Language :: Python :: 3.9
Classifier: Programming Language :: Python :: 3.10
Classifier: Programming Language :: Python :: 3.11
Classifier: Topic :: Software Development :: Testing
Requires-Python: >=3.9
License-File: LICENSE
Dynamic: license-file
